guardrails/__init__.py
guardrails/actions/__init__.py
guardrails/actions/filter.py
guardrails/actions/reask.py
guardrails/actions/refrain.py
guardrails/api_client.py
guardrails/applications/__init__.py
guardrails/applications/text2sql.py
guardrails/applications/text2sql.rail
guardrails/async_guard.py
guardrails/call_tracing/__init__.py
guardrails/call_tracing/sqlite_trace_handler.py
guardrails/call_tracing/trace_entry.py
guardrails/call_tracing/trace_handler.py
guardrails/call_tracing/tracer_mixin.py
guardrails/classes/__init__.py
guardrails/classes/credentials.py
guardrails/classes/execution/__init__.py
guardrails/classes/execution/guard_execution_options.py
guardrails/classes/generic/__init__.py
guardrails/classes/generic/arbitrary_model.py
guardrails/classes/generic/default_json_encoder.py
guardrails/classes/generic/serializeable.py
guardrails/classes/generic/stack.py
guardrails/classes/history/__init__.py
guardrails/classes/history/call.py
guardrails/classes/history/call_inputs.py
guardrails/classes/history/inputs.py
guardrails/classes/history/iteration.py
guardrails/classes/history/outputs.py
guardrails/classes/input_type.py
guardrails/classes/llm/llm_response.py
guardrails/classes/llm/prompt_callable.py
guardrails/classes/output_type.py
guardrails/classes/rc.py
guardrails/classes/schema/__init__.py
guardrails/classes/schema/model_schema.py
guardrails/classes/schema/processed_schema.py
guardrails/classes/templating/constants_container.py
guardrails/classes/templating/namespace_template.py
guardrails/classes/validation/validation_result.py
guardrails/classes/validation/validation_summary.py
guardrails/classes/validation/validator_logs.py
guardrails/classes/validation/validator_reference.py
guardrails/classes/validation_outcome.py
guardrails/cli/__init__.py
guardrails/cli/configure.py
guardrails/cli/create.py
guardrails/cli/guardrails.py
guardrails/cli/hub/__init__.py
guardrails/cli/hub/console.py
guardrails/cli/hub/create_validator.py
guardrails/cli/hub/hub.py
guardrails_ai-0.7.2.dist-info/METADATA
guardrails_ai-0.7.2.dist-info/WHEEL
guardrails_ai-0.7.2.dist-info/entry_points.txt
guardrails_ai-0.7.2.dist-info/licenses/LICENSE
guardrails_ai-0.7.2.dist-info/RECORD
