Metadata-Version: 2.4
Name: guardrails-ai
Version: 0.7.2
Summary: Adding guardrails to large language models.
License: Apache-2.0
License-File: LICENSE
Author: Guardrails AI
Author-email: contact@guardrailsai.com
Requires-Python: >=3.10,<4.0
Classifier: License :: OSI Approved :: Apache Software License
Classifier: Programming Language :: Python :: 3
Classifier: Programming Language :: Python :: 3.10
Classifier: Programming Language :: Python :: 3.11
Classifier: Programming Language :: Python :: 3.12
Classifier: Programming Language :: Python :: 3.13
Classifier: Programming Language :: Python :: 3.14
Provides-Extra: anthropic
Provides-Extra: api
Provides-Extra: databricks
Provides-Extra: dev
Provides-Extra: docs
Provides-Extra: docs-build
Provides-Extra: huggingface
Provides-Extra: llama
Provides-Extra: manifest
Provides-Extra: sql
Provides-Extra: uv
Provides-Extra: vectordb
Requires-Dist: anthropic (>=0.7.2,<1.0.0) ; extra == "anthropic"
Requires-Dist: boto3 (>1,<2) ; extra == "api"
Requires-Dist: cairosvg (>=2.7.1) ; extra == "docs"
Requires-Dist: click (<=8.2.0)
Requires-Dist: diff-match-patch (>=20230430,<20241101)
Requires-Dist: docformatter (>=1.4) ; extra == "dev"
Requires-Dist: docspec_python (==2.2.1) ; extra == "docs-build"
Requires-Dist: faiss-cpu (>=1.7.4,<2.0.0) ; extra == "vectordb"
Requires-Dist: faker (>=25.2.0,<38.0.0)
Requires-Dist: griffe (>=1.3.2) ; extra == "docs"
Requires-Dist: guardrails-api (>=0.1.0a1,<0.2.0) ; extra == "api"
Requires-Dist: guardrails-api-client (==0.4.0a1) ; python_version < "3.10"
Requires-Dist: guardrails-api-client (>=0.4.0,<0.5.0) ; python_version >= "3.10"
Requires-Dist: guardrails-hub-types (>=0.0.4,<0.1.0)
Requires-Dist: guardrails-jsonformer (>=0.13.1,<1.0.0) ; extra == "huggingface"
Requires-Dist: jsonref (>=1.1.0,<2.0.0)
Requires-Dist: jsonschema[format-nongpl] (>=4.22.0,<5.0.0)
Requires-Dist: langchain-core (>=1.0.0,<2.0)
Requires-Dist: liccheck (>=0.9.2) ; extra == "dev"
Requires-Dist: litellm (>=1.37.14,<2.0.0)
Requires-Dist: llama-index (>=0.11.0,<1.0.0) ; extra == "llama"
Requires-Dist: lxml (>=4.9.3,<7.0.0)
Requires-Dist: lxml-stubs (>=0.4.0) ; extra == "dev"
Requires-Dist: manifest-ml (>=0.1.8,<0.2.0) ; extra == "manifest"
Requires-Dist: mkdocs (>=1.5.3) ; extra == "docs"
Requires-Dist: mkdocs-glightbox (>=0.3.4) ; extra == "docs"
Requires-Dist: mkdocs-jupyter (>=0.23) ; extra == "docs"
Requires-Dist: mkdocs-material (>=9.4.8) ; extra == "docs"
Requires-Dist: mkdocstrings[python] (>=0.23.0) ; extra == "docs"
Requires-Dist: mknotebooks (>=0.8.0) ; extra == "docs"
Requires-Dist: mlflow (>=2.0.1,<4.0.0) ; extra == "databricks"
Requires-Dist: nbdoc (>=0.0.82,<0.1.0) ; extra == "docs-build"
Requires-Dist: numpy (>=1.25,<3.0) ; extra == "vectordb"
Requires-Dist: openai (>=1.30.1,<2.0.0)
Requires-Dist: opentelemetry-exporter-otlp-proto-grpc (>=1.24.0,<2.0.0)
Requires-Dist: opentelemetry-exporter-otlp-proto-http (>=1.24.0,<2.0.0)
Requires-Dist: opentelemetry-sdk (>=1.24.0,<2.0.0)
Requires-Dist: pillow (>=10.1.0) ; extra == "docs"
Requires-Dist: pip (>=22)
Requires-Dist: pre-commit (>=2.9.3) ; extra == "dev"
Requires-Dist: pydantic (>=2.0.0,<3.0)
Requires-Dist: pydash (>=7.0.6,<9.0.0)
Requires-Dist: pydoc-markdown (==4.8.2) ; extra == "docs-build"
Requires-Dist: pyjwt (>=2.8.0,<3.0.0)
Requires-Dist: pypdfium2 (>=4.23.1) ; extra == "dev"
Requires-Dist: pyright (==1.1.334) ; extra == "dev"
Requires-Dist: pytest (>=7.4.3) ; extra == "dev"
Requires-Dist: pytest-asyncio (>=0.21.1) ; extra == "dev"
Requires-Dist: pytest-cov (>=2.10.1) ; extra == "dev"
Requires-Dist: pytest-mock (>=3.12.0) ; extra == "dev"
Requires-Dist: python-dateutil (>=2.8.2,<3.0.0)
Requires-Dist: requests (>=2.31.0,<3.0.0)
Requires-Dist: rich (>=13.6.0,<15.0.0)
Requires-Dist: rstr (>=3.2.2,<4.0.0)
Requires-Dist: ruff (>=0.4.1) ; extra == "dev"
Requires-Dist: semver (>=3.0.2,<4.0.0)
Requires-Dist: sqlalchemy (>=2.0.9,<3.0.0) ; extra == "sql"
Requires-Dist: sqlglot (>=19.0.3,<20.0.0) ; extra == "sql"
Requires-Dist: sqlvalidator (>=0.0.20,<0.1.0) ; extra == "sql"
Requires-Dist: tenacity (>=8.1.0,<10.0.0)
Requires-Dist: tiktoken (>=0.5.1,<1.0.0)
Requires-Dist: torch (>=2.1.1,<3.0.0) ; extra == "huggingface"
Requires-Dist: transformers (>=4.38.0,<5.0.0) ; extra == "huggingface"
Requires-Dist: twine (>=4.0.2) ; extra == "dev"
Requires-Dist: typer (>=0.9.0,<0.20)
Requires-Dist: typing-extensions (>=4.8.0,<5.0.0)
Requires-Dist: uvloop (>=0.20.0,<1.0.0) ; extra == "uv"
